<annotation>
	<folder>img</folder>
	<filename>1img194.jpg</filename>
	<path>C:\Users\Lenovo\Desktop\打标签\宋珂\img\1img194.jpg</path>
	<source>
		<database>Unknown</database>
	</source>
	<size>
		<width>2560</width>
		<height>1440</height>
		<depth>3</depth>
	</size>
	<segmented>0</segmented>
	<object>
		<name>truck</name>
		<pose>Unspecified</pose>
		<truncated>0</truncated>
		<difficult>0</difficult>
		<bndbox>
			<xmin>1076</xmin>
			<ymin>178</ymin>
			<xmax>2542</xmax>
			<ymax>1439</ymax>
		</bndbox>
	</object>
	<object>
		<name>people</name>
		<pose>Unspecified</pose>
		<truncated>0</truncated>
		<difficult>0</difficult>
		<bndbox>
			<xmin>1770</xmin>
			<ymin>347</ymin>
			<xmax>1977</xmax>
			<ymax>904</ymax>
		</bndbox>
	</object>
	<object>
		<name>helmet</name>
		<pose>Unspecified</pose>
		<truncated>0</truncated>
		<difficult>0</difficult>
		<bndbox>
			<xmin>1861</xmin>
			<ymin>347</ymin>
			<xmax>1936</xmax>
			<ymax>409</ymax>
		</bndbox>
	</object>
	<object>
		<name>head</name>
		<pose>Unspecified</pose>
		<truncated>0</truncated>
		<difficult>0</difficult>
		<bndbox>
			<xmin>1790</xmin>
			<ymin>348</ymin>
			<xmax>1976</xmax>
			<ymax>513</ymax>
		</bndbox>
	</object>
	<object>
		<name>belt</name>
		<pose>Unspecified</pose>
		<truncated>0</truncated>
		<difficult>0</difficult>
		<bndbox>
			<xmin>1849</xmin>
			<ymin>431</ymin>
			<xmax>1931</xmax>
			<ymax>519</ymax>
		</bndbox>
	</object>
	<object>
		<name>people</name>
		<pose>Unspecified</pose>
		<truncated>0</truncated>
		<difficult>0</difficult>
		<bndbox>
			<xmin>2103</xmin>
			<ymin>600</ymin>
			<xmax>2213</xmax>
			<ymax>1129</ymax>
		</bndbox>
	</object>
	<object>
		<name>helmet</name>
		<pose>Unspecified</pose>
		<truncated>0</truncated>
		<difficult>0</difficult>
		<bndbox>
			<xmin>2103</xmin>
			<ymin>602</ymin>
			<xmax>2188</xmax>
			<ymax>696</ymax>
		</bndbox>
	</object>
	<object>
		<name>head</name>
		<pose>Unspecified</pose>
		<truncated>0</truncated>
		<difficult>0</difficult>
		<bndbox>
			<xmin>2104</xmin>
			<ymin>602</ymin>
			<xmax>2212</xmax>
			<ymax>733</ymax>
		</bndbox>
	</object>
	<object>
		<name>people</name>
		<pose>Unspecified</pose>
		<truncated>0</truncated>
		<difficult>0</difficult>
		<bndbox>
			<xmin>2170</xmin>
			<ymin>624</ymin>
			<xmax>2370</xmax>
			<ymax>1270</ymax>
		</bndbox>
	</object>
	<object>
		<name>helmet</name>
		<pose>Unspecified</pose>
		<truncated>0</truncated>
		<difficult>0</difficult>
		<bndbox>
			<xmin>2192</xmin>
			<ymin>624</ymin>
			<xmax>2309</xmax>
			<ymax>712</ymax>
		</bndbox>
	</object>
	<object>
		<name>head</name>
		<pose>Unspecified</pose>
		<truncated>0</truncated>
		<difficult>0</difficult>
		<bndbox>
			<xmin>2192</xmin>
			<ymin>626</ymin>
			<xmax>2358</xmax>
			<ymax>846</ymax>
		</bndbox>
	</object>
	<object>
		<name>belt</name>
		<pose>Unspecified</pose>
		<truncated>0</truncated>
		<difficult>0</difficult>
		<bndbox>
			<xmin>2186</xmin>
			<ymin>756</ymin>
			<xmax>2373</xmax>
			<ymax>986</ymax>
		</bndbox>
	</object>
</annotation>
