<annotation>
	<folder>2img</folder>
	<filename>2img25.jpg</filename>
	<path>G:\熊政杰\熊政杰\2img\2img25.jpg</path>
	<source>
		<database>Unknown</database>
	</source>
	<size>
		<width>2560</width>
		<height>1440</height>
		<depth>3</depth>
	</size>
	<segmented>0</segmented>
	<object>
		<name>truck</name>
		<pose>Unspecified</pose>
		<truncated>1</truncated>
		<difficult>0</difficult>
		<bndbox>
			<xmin>1061</xmin>
			<ymin>140</ymin>
			<xmax>2560</xmax>
			<ymax>1440</ymax>
		</bndbox>
	</object>
	<object>
		<name>people</name>
		<pose>Unspecified</pose>
		<truncated>0</truncated>
		<difficult>0</difficult>
		<bndbox>
			<xmin>2183</xmin>
			<ymin>805</ymin>
			<xmax>2425</xmax>
			<ymax>1438</ymax>
		</bndbox>
	</object>
	<object>
		<name>people</name>
		<pose>Unspecified</pose>
		<truncated>0</truncated>
		<difficult>0</difficult>
		<bndbox>
			<xmin>1594</xmin>
			<ymin>168</ymin>
			<xmax>1733</xmax>
			<ymax>366</ymax>
		</bndbox>
	</object>
	<object>
		<name>helmet</name>
		<pose>Unspecified</pose>
		<truncated>0</truncated>
		<difficult>0</difficult>
		<bndbox>
			<xmin>1586</xmin>
			<ymin>173</ymin>
			<xmax>1635</xmax>
			<ymax>229</ymax>
		</bndbox>
	</object>
	<object>
		<name>helmet</name>
		<pose>Unspecified</pose>
		<truncated>0</truncated>
		<difficult>0</difficult>
		<bndbox>
			<xmin>2222</xmin>
			<ymin>807</ymin>
			<xmax>2329</xmax>
			<ymax>931</ymax>
		</bndbox>
	</object>
	<object>
		<name>head</name>
		<pose>Unspecified</pose>
		<truncated>0</truncated>
		<difficult>0</difficult>
		<bndbox>
			<xmin>1583</xmin>
			<ymin>175</ymin>
			<xmax>1712</xmax>
			<ymax>277</ymax>
		</bndbox>
	</object>
	<object>
		<name>head</name>
		<pose>Unspecified</pose>
		<truncated>0</truncated>
		<difficult>0</difficult>
		<bndbox>
			<xmin>2225</xmin>
			<ymin>818</ymin>
			<xmax>2427</xmax>
			<ymax>988</ymax>
		</bndbox>
	</object>
	<object>
		<name>belt</name>
		<pose>Unspecified</pose>
		<truncated>0</truncated>
		<difficult>0</difficult>
		<bndbox>
			<xmin>1642</xmin>
			<ymin>212</ymin>
			<xmax>1716</xmax>
			<ymax>292</ymax>
		</bndbox>
	</object>
	<object>
		<name>belt</name>
		<pose>Unspecified</pose>
		<truncated>0</truncated>
		<difficult>0</difficult>
		<bndbox>
			<xmin>2292</xmin>
			<ymin>859</ymin>
			<xmax>2425</xmax>
			<ymax>1049</ymax>
		</bndbox>
	</object>
</annotation>
