<annotation>
	<folder>李俊宇</folder>
	<filename>5img5.jpg</filename>
	<path>C:\Users\lijunyu\Desktop\李俊宇111\李俊宇\5img5.jpg</path>
	<source>
		<database>Unknown</database>
	</source>
	<size>
		<width>2560</width>
		<height>1440</height>
		<depth>3</depth>
	</size>
	<segmented>0</segmented>
	<object>
		<name>truck</name>
		<pose>Unspecified</pose>
		<truncated>1</truncated>
		<difficult>0</difficult>
		<bndbox>
			<xmin>1179</xmin>
			<ymin>261</ymin>
			<xmax>2560</xmax>
			<ymax>1440</ymax>
		</bndbox>
	</object>
	<object>
		<name>people</name>
		<pose>Unspecified</pose>
		<truncated>0</truncated>
		<difficult>0</difficult>
		<bndbox>
			<xmin>1178</xmin>
			<ymin>518</ymin>
			<xmax>1254</xmax>
			<ymax>813</ymax>
		</bndbox>
	</object>
	<object>
		<name>head</name>
		<pose>Unspecified</pose>
		<truncated>0</truncated>
		<difficult>0</difficult>
		<bndbox>
			<xmin>2091</xmin>
			<ymin>517</ymin>
			<xmax>2357</xmax>
			<ymax>832</ymax>
		</bndbox>
	</object>
	<object>
		<name>helmet</name>
		<pose>Unspecified</pose>
		<truncated>0</truncated>
		<difficult>0</difficult>
		<bndbox>
			<xmin>2178</xmin>
			<ymin>518</ymin>
			<xmax>2264</xmax>
			<ymax>628</ymax>
		</bndbox>
	</object>
	<object>
		<name>belt</name>
		<pose>Unspecified</pose>
		<truncated>0</truncated>
		<difficult>0</difficult>
		<bndbox>
			<xmin>2145</xmin>
			<ymin>606</ymin>
			<xmax>2279</xmax>
			<ymax>725</ymax>
		</bndbox>
	</object>
</annotation>
