<annotation>
	<folder>李俊宇</folder>
	<filename>5img205.jpg</filename>
	<path>C:\Users\lijunyu\Desktop\李俊宇111\李俊宇\5img205.jpg</path>
	<source>
		<database>Unknown</database>
	</source>
	<size>
		<width>2560</width>
		<height>1440</height>
		<depth>3</depth>
	</size>
	<segmented>0</segmented>
	<object>
		<name>truck</name>
		<pose>Unspecified</pose>
		<truncated>1</truncated>
		<difficult>0</difficult>
		<bndbox>
			<xmin>1180</xmin>
			<ymin>266</ymin>
			<xmax>2560</xmax>
			<ymax>1440</ymax>
		</bndbox>
	</object>
	<object>
		<name>people</name>
		<pose>Unspecified</pose>
		<truncated>0</truncated>
		<difficult>0</difficult>
		<bndbox>
			<xmin>1561</xmin>
			<ymin>273</ymin>
			<xmax>1882</xmax>
			<ymax>582</ymax>
		</bndbox>
	</object>
	<object>
		<name>head</name>
		<pose>Unspecified</pose>
		<truncated>0</truncated>
		<difficult>0</difficult>
		<bndbox>
			<xmin>1728</xmin>
			<ymin>276</ymin>
			<xmax>1846</xmax>
			<ymax>423</ymax>
		</bndbox>
	</object>
	<object>
		<name>helmet</name>
		<pose>Unspecified</pose>
		<truncated>0</truncated>
		<difficult>0</difficult>
		<bndbox>
			<xmin>1744</xmin>
			<ymin>271</ymin>
			<xmax>1815</xmax>
			<ymax>330</ymax>
		</bndbox>
	</object>
	<object>
		<name>belt</name>
		<pose>Unspecified</pose>
		<truncated>0</truncated>
		<difficult>0</difficult>
		<bndbox>
			<xmin>1723</xmin>
			<ymin>359</ymin>
			<xmax>1827</xmax>
			<ymax>456</ymax>
		</bndbox>
	</object>
</annotation>
