<annotation>
	<folder>imges</folder>
	<filename>aimg187.jpg</filename>
	<path>C:\Users\lijunyu\Desktop\LJY\imges\aimg187.jpg</path>
	<source>
		<database>Unknown</database>
	</source>
	<size>
		<width>2560</width>
		<height>1440</height>
		<depth>3</depth>
	</size>
	<segmented>0</segmented>
	<object>
		<name>truck</name>
		<pose>Unspecified</pose>
		<truncated>1</truncated>
		<difficult>0</difficult>
		<bndbox>
			<xmin>939</xmin>
			<ymin>45</ymin>
			<xmax>2560</xmax>
			<ymax>1440</ymax>
		</bndbox>
	</object>
	<object>
		<name>people</name>
		<pose>Unspecified</pose>
		<truncated>0</truncated>
		<difficult>0</difficult>
		<bndbox>
			<xmin>2179</xmin>
			<ymin>557</ymin>
			<xmax>2417</xmax>
			<ymax>1133</ymax>
		</bndbox>
	</object>
	<object>
		<name>people</name>
		<pose>Unspecified</pose>
		<truncated>0</truncated>
		<difficult>0</difficult>
		<bndbox>
			<xmin>1516</xmin>
			<ymin>273</ymin>
			<xmax>1691</xmax>
			<ymax>532</ymax>
		</bndbox>
	</object>
	<object>
		<name>head</name>
		<pose>Unspecified</pose>
		<truncated>0</truncated>
		<difficult>0</difficult>
		<bndbox>
			<xmin>2208</xmin>
			<ymin>557</ymin>
			<xmax>2393</xmax>
			<ymax>733</ymax>
		</bndbox>
	</object>
	<object>
		<name>head</name>
		<pose>Unspecified</pose>
		<truncated>0</truncated>
		<difficult>0</difficult>
		<bndbox>
			<xmin>1569</xmin>
			<ymin>274</ymin>
			<xmax>1661</xmax>
			<ymax>370</ymax>
		</bndbox>
	</object>
	<object>
		<name>helmet</name>
		<pose>Unspecified</pose>
		<truncated>0</truncated>
		<difficult>0</difficult>
		<bndbox>
			<xmin>2296</xmin>
			<ymin>555</ymin>
			<xmax>2370</xmax>
			<ymax>632</ymax>
		</bndbox>
	</object>
	<object>
		<name>helmet</name>
		<pose>Unspecified</pose>
		<truncated>0</truncated>
		<difficult>0</difficult>
		<bndbox>
			<xmin>1606</xmin>
			<ymin>275</ymin>
			<xmax>1654</xmax>
			<ymax>310</ymax>
		</bndbox>
	</object>
	<object>
		<name>belt</name>
		<pose>Unspecified</pose>
		<truncated>0</truncated>
		<difficult>0</difficult>
		<bndbox>
			<xmin>1585</xmin>
			<ymin>297</ymin>
			<xmax>1654</xmax>
			<ymax>344</ymax>
		</bndbox>
	</object>
	<object>
		<name>belt</name>
		<pose>Unspecified</pose>
		<truncated>0</truncated>
		<difficult>0</difficult>
		<bndbox>
			<xmin>2220</xmin>
			<ymin>620</ymin>
			<xmax>2376</xmax>
			<ymax>781</ymax>
		</bndbox>
	</object>
</annotation>
