<annotation>
	<folder>imges</folder>
	<filename>aimg325.jpg</filename>
	<path>E:\LZH\LZH\imges\aimg325.jpg</path>
	<source>
		<database>Unknown</database>
	</source>
	<size>
		<width>2560</width>
		<height>1440</height>
		<depth>3</depth>
	</size>
	<segmented>0</segmented>
	<object>
		<name>head</name>
		<pose>Unspecified</pose>
		<truncated>0</truncated>
		<difficult>0</difficult>
		<bndbox>
			<xmin>1508</xmin>
			<ymin>100</ymin>
			<xmax>1622</xmax>
			<ymax>200</ymax>
		</bndbox>
	</object>
	<object>
		<name>helmet</name>
		<pose>Unspecified</pose>
		<truncated>0</truncated>
		<difficult>0</difficult>
		<bndbox>
			<xmin>1560</xmin>
			<ymin>101</ymin>
			<xmax>1619</xmax>
			<ymax>155</ymax>
		</bndbox>
	</object>
	<object>
		<name>head</name>
		<pose>Unspecified</pose>
		<truncated>0</truncated>
		<difficult>0</difficult>
		<bndbox>
			<xmin>1412</xmin>
			<ymin>449</ymin>
			<xmax>1545</xmax>
			<ymax>562</ymax>
		</bndbox>
	</object>
	<object>
		<name>belt</name>
		<pose>Unspecified</pose>
		<truncated>0</truncated>
		<difficult>0</difficult>
		<bndbox>
			<xmin>1477</xmin>
			<ymin>143</ymin>
			<xmax>1575</xmax>
			<ymax>239</ymax>
		</bndbox>
	</object>
	<object>
		<name>belt</name>
		<pose>Unspecified</pose>
		<truncated>0</truncated>
		<difficult>0</difficult>
		<bndbox>
			<xmin>1478</xmin>
			<ymin>399</ymin>
			<xmax>1600</xmax>
			<ymax>536</ymax>
		</bndbox>
	</object>
	<object>
		<name>helmet</name>
		<pose>Unspecified</pose>
		<truncated>0</truncated>
		<difficult>0</difficult>
		<bndbox>
			<xmin>1413</xmin>
			<ymin>489</ymin>
			<xmax>1477</xmax>
			<ymax>560</ymax>
		</bndbox>
	</object>
	<object>
		<name>helmet</name>
		<pose>Unspecified</pose>
		<truncated>0</truncated>
		<difficult>0</difficult>
		<bndbox>
			<xmin>1877</xmin>
			<ymin>460</ymin>
			<xmax>1964</xmax>
			<ymax>536</ymax>
		</bndbox>
	</object>
	<object>
		<name>belt</name>
		<pose>Unspecified</pose>
		<truncated>0</truncated>
		<difficult>0</difficult>
		<bndbox>
			<xmin>1943</xmin>
			<ymin>533</ymin>
			<xmax>2074</xmax>
			<ymax>647</ymax>
		</bndbox>
	</object>
	<object>
		<name>head</name>
		<pose>Unspecified</pose>
		<truncated>0</truncated>
		<difficult>0</difficult>
		<bndbox>
			<xmin>1877</xmin>
			<ymin>459</ymin>
			<xmax>2044</xmax>
			<ymax>596</ymax>
		</bndbox>
	</object>
	<object>
		<name>people</name>
		<pose>Unspecified</pose>
		<truncated>0</truncated>
		<difficult>0</difficult>
		<bndbox>
			<xmin>1445</xmin>
			<ymin>102</ymin>
			<xmax>1650</xmax>
			<ymax>385</ymax>
		</bndbox>
	</object>
	<object>
		<name>people</name>
		<pose>Unspecified</pose>
		<truncated>0</truncated>
		<difficult>0</difficult>
		<bndbox>
			<xmin>1410</xmin>
			<ymin>426</ymin>
			<xmax>1696</xmax>
			<ymax>628</ymax>
		</bndbox>
	</object>
	<object>
		<name>people</name>
		<pose>Unspecified</pose>
		<truncated>0</truncated>
		<difficult>0</difficult>
		<bndbox>
			<xmin>1879</xmin>
			<ymin>458</ymin>
			<xmax>2188</xmax>
			<ymax>1001</ymax>
		</bndbox>
	</object>
	<object>
		<name>truck</name>
		<pose>Unspecified</pose>
		<truncated>0</truncated>
		<difficult>0</difficult>
		<bndbox>
			<xmin>1104</xmin>
			<ymin>123</ymin>
			<xmax>2557</xmax>
			<ymax>1437</ymax>
		</bndbox>
	</object>
</annotation>
