<annotation>
	<folder>imges</folder>
	<filename>aimg204.jpg</filename>
	<path>C:\Users\lijunyu\Desktop\LJY\imges\aimg204.jpg</path>
	<source>
		<database>Unknown</database>
	</source>
	<size>
		<width>2560</width>
		<height>1440</height>
		<depth>3</depth>
	</size>
	<segmented>0</segmented>
	<object>
		<name>truck</name>
		<pose>Unspecified</pose>
		<truncated>1</truncated>
		<difficult>0</difficult>
		<bndbox>
			<xmin>1156</xmin>
			<ymin>376</ymin>
			<xmax>2560</xmax>
			<ymax>1440</ymax>
		</bndbox>
	</object>
	<object>
		<name>people</name>
		<pose>Unspecified</pose>
		<truncated>0</truncated>
		<difficult>0</difficult>
		<bndbox>
			<xmin>1997</xmin>
			<ymin>386</ymin>
			<xmax>2351</xmax>
			<ymax>1077</ymax>
		</bndbox>
	</object>
	<object>
		<name>people</name>
		<pose>Unspecified</pose>
		<truncated>0</truncated>
		<difficult>0</difficult>
		<bndbox>
			<xmin>1757</xmin>
			<ymin>212</ymin>
			<xmax>1929</xmax>
			<ymax>703</ymax>
		</bndbox>
	</object>
	<object>
		<name>people</name>
		<pose>Unspecified</pose>
		<truncated>0</truncated>
		<difficult>0</difficult>
		<bndbox>
			<xmin>1865</xmin>
			<ymin>277</ymin>
			<xmax>2062</xmax>
			<ymax>832</ymax>
		</bndbox>
	</object>
	<object>
		<name>head</name>
		<pose>Unspecified</pose>
		<truncated>0</truncated>
		<difficult>0</difficult>
		<bndbox>
			<xmin>1769</xmin>
			<ymin>215</ymin>
			<xmax>1898</xmax>
			<ymax>395</ymax>
		</bndbox>
	</object>
	<object>
		<name>head</name>
		<pose>Unspecified</pose>
		<truncated>0</truncated>
		<difficult>0</difficult>
		<bndbox>
			<xmin>1890</xmin>
			<ymin>279</ymin>
			<xmax>2015</xmax>
			<ymax>466</ymax>
		</bndbox>
	</object>
	<object>
		<name>head</name>
		<pose>Unspecified</pose>
		<truncated>0</truncated>
		<difficult>0</difficult>
		<bndbox>
			<xmin>2116</xmin>
			<ymin>390</ymin>
			<xmax>2292</xmax>
			<ymax>607</ymax>
		</bndbox>
	</object>
	<object>
		<name>helmet</name>
		<pose>Unspecified</pose>
		<truncated>0</truncated>
		<difficult>0</difficult>
		<bndbox>
			<xmin>1806</xmin>
			<ymin>213</ymin>
			<xmax>1892</xmax>
			<ymax>281</ymax>
		</bndbox>
	</object>
	<object>
		<name>helmet</name>
		<pose>Unspecified</pose>
		<truncated>0</truncated>
		<difficult>0</difficult>
		<bndbox>
			<xmin>1889</xmin>
			<ymin>243</ymin>
			<xmax>1954</xmax>
			<ymax>308</ymax>
		</bndbox>
	</object>
	<object>
		<name>helmet</name>
		<pose>Unspecified</pose>
		<truncated>0</truncated>
		<difficult>0</difficult>
		<bndbox>
			<xmin>1927</xmin>
			<ymin>277</ymin>
			<xmax>2000</xmax>
			<ymax>340</ymax>
		</bndbox>
	</object>
	<object>
		<name>helmet</name>
		<pose>Unspecified</pose>
		<truncated>0</truncated>
		<difficult>0</difficult>
		<bndbox>
			<xmin>2170</xmin>
			<ymin>388</ymin>
			<xmax>2273</xmax>
			<ymax>457</ymax>
		</bndbox>
	</object>
	<object>
		<name>belt</name>
		<pose>Unspecified</pose>
		<truncated>0</truncated>
		<difficult>0</difficult>
		<bndbox>
			<xmin>1792</xmin>
			<ymin>298</ymin>
			<xmax>1881</xmax>
			<ymax>362</ymax>
		</bndbox>
	</object>
	<object>
		<name>belt</name>
		<pose>Unspecified</pose>
		<truncated>0</truncated>
		<difficult>0</difficult>
		<bndbox>
			<xmin>1878</xmin>
			<ymin>360</ymin>
			<xmax>2006</xmax>
			<ymax>509</ymax>
		</bndbox>
	</object>
	<object>
		<name>belt</name>
		<pose>Unspecified</pose>
		<truncated>0</truncated>
		<difficult>0</difficult>
		<bndbox>
			<xmin>2105</xmin>
			<ymin>502</ymin>
			<xmax>2295</xmax>
			<ymax>675</ymax>
		</bndbox>
	</object>
</annotation>
