<annotation>
	<folder>imges</folder>
	<filename>aimg453.jpg</filename>
	<path>E:\LZH\LZH\imges\aimg453.jpg</path>
	<source>
		<database>Unknown</database>
	</source>
	<size>
		<width>2560</width>
		<height>1440</height>
		<depth>3</depth>
	</size>
	<segmented>0</segmented>
	<object>
		<name>belt</name>
		<pose>Unspecified</pose>
		<truncated>0</truncated>
		<difficult>0</difficult>
		<bndbox>
			<xmin>1704</xmin>
			<ymin>154</ymin>
			<xmax>1785</xmax>
			<ymax>219</ymax>
		</bndbox>
	</object>
	<object>
		<name>helmet</name>
		<pose>Unspecified</pose>
		<truncated>0</truncated>
		<difficult>0</difficult>
		<bndbox>
			<xmin>1739</xmin>
			<ymin>101</ymin>
			<xmax>1807</xmax>
			<ymax>163</ymax>
		</bndbox>
	</object>
	<object>
		<name>belt</name>
		<pose>Unspecified</pose>
		<truncated>0</truncated>
		<difficult>0</difficult>
		<bndbox>
			<xmin>1838</xmin>
			<ymin>421</ymin>
			<xmax>1935</xmax>
			<ymax>546</ymax>
		</bndbox>
	</object>
	<object>
		<name>head</name>
		<pose>Unspecified</pose>
		<truncated>0</truncated>
		<difficult>0</difficult>
		<bndbox>
			<xmin>1675</xmin>
			<ymin>99</ymin>
			<xmax>1807</xmax>
			<ymax>220</ymax>
		</bndbox>
	</object>
	<object>
		<name>head</name>
		<pose>Unspecified</pose>
		<truncated>0</truncated>
		<difficult>0</difficult>
		<bndbox>
			<xmin>1811</xmin>
			<ymin>370</ymin>
			<xmax>1975</xmax>
			<ymax>493</ymax>
		</bndbox>
	</object>
	<object>
		<name>helmet</name>
		<pose>Unspecified</pose>
		<truncated>0</truncated>
		<difficult>0</difficult>
		<bndbox>
			<xmin>1891</xmin>
			<ymin>370</ymin>
			<xmax>1973</xmax>
			<ymax>451</ymax>
		</bndbox>
	</object>
	<object>
		<name>helmet</name>
		<pose>Unspecified</pose>
		<truncated>0</truncated>
		<difficult>0</difficult>
		<bndbox>
			<xmin>1884</xmin>
			<ymin>493</ymin>
			<xmax>1976</xmax>
			<ymax>597</ymax>
		</bndbox>
	</object>
	<object>
		<name>head</name>
		<pose>Unspecified</pose>
		<truncated>0</truncated>
		<difficult>0</difficult>
		<bndbox>
			<xmin>1883</xmin>
			<ymin>491</ymin>
			<xmax>2059</xmax>
			<ymax>664</ymax>
		</bndbox>
	</object>
	<object>
		<name>belt</name>
		<pose>Unspecified</pose>
		<truncated>0</truncated>
		<difficult>0</difficult>
		<bndbox>
			<xmin>1953</xmin>
			<ymin>557</ymin>
			<xmax>2095</xmax>
			<ymax>708</ymax>
		</bndbox>
	</object>
	<object>
		<name>truck</name>
		<pose>Unspecified</pose>
		<truncated>0</truncated>
		<difficult>0</difficult>
		<bndbox>
			<xmin>1102</xmin>
			<ymin>134</ymin>
			<xmax>2558</xmax>
			<ymax>1436</ymax>
		</bndbox>
	</object>
	<object>
		<name>people</name>
		<pose>Unspecified</pose>
		<truncated>0</truncated>
		<difficult>0</difficult>
		<bndbox>
			<xmin>1633</xmin>
			<ymin>97</ymin>
			<xmax>1809</xmax>
			<ymax>511</ymax>
		</bndbox>
	</object>
	<object>
		<name>people</name>
		<pose>Unspecified</pose>
		<truncated>0</truncated>
		<difficult>0</difficult>
		<bndbox>
			<xmin>1853</xmin>
			<ymin>491</ymin>
			<xmax>2080</xmax>
			<ymax>1159</ymax>
		</bndbox>
	</object>
</annotation>
