<annotation>
	<folder>imges</folder>
	<filename>aimg1234.jpg</filename>
	<path>C:\Users\17818\Desktop\imges\aimg1234.jpg</path>
	<source>
		<database>Unknown</database>
	</source>
	<size>
		<width>2560</width>
		<height>1440</height>
		<depth>3</depth>
	</size>
	<segmented>0</segmented>
	<object>
		<name>belt</name>
		<pose>Unspecified</pose>
		<truncated>0</truncated>
		<difficult>0</difficult>
		<bndbox>
			<xmin>2102</xmin>
			<ymin>624</ymin>
			<xmax>2227</xmax>
			<ymax>757</ymax>
		</bndbox>
	</object>
	<object>
		<name>helmet</name>
		<pose>Unspecified</pose>
		<truncated>0</truncated>
		<difficult>0</difficult>
		<bndbox>
			<xmin>2003</xmin>
			<ymin>519</ymin>
			<xmax>2104</xmax>
			<ymax>613</ymax>
		</bndbox>
	</object>
	<object>
		<name>head</name>
		<pose>Unspecified</pose>
		<truncated>0</truncated>
		<difficult>0</difficult>
		<bndbox>
			<xmin>1325</xmin>
			<ymin>140</ymin>
			<xmax>1463</xmax>
			<ymax>234</ymax>
		</bndbox>
	</object>
	<object>
		<name>head</name>
		<pose>Unspecified</pose>
		<truncated>0</truncated>
		<difficult>0</difficult>
		<bndbox>
			<xmin>1563</xmin>
			<ymin>403</ymin>
			<xmax>1692</xmax>
			<ymax>540</ymax>
		</bndbox>
	</object>
	<object>
		<name>belt</name>
		<pose>Unspecified</pose>
		<truncated>0</truncated>
		<difficult>0</difficult>
		<bndbox>
			<xmin>1595</xmin>
			<ymin>468</ymin>
			<xmax>1713</xmax>
			<ymax>574</ymax>
		</bndbox>
	</object>
	<object>
		<name>people</name>
		<pose>Unspecified</pose>
		<truncated>0</truncated>
		<difficult>0</difficult>
		<bndbox>
			<xmin>2067</xmin>
			<ymin>523</ymin>
			<xmax>2202</xmax>
			<ymax>1083</ymax>
		</bndbox>
	</object>
	<object>
		<name>helmet</name>
		<pose>Unspecified</pose>
		<truncated>0</truncated>
		<difficult>0</difficult>
		<bndbox>
			<xmin>2076</xmin>
			<ymin>539</ymin>
			<xmax>2155</xmax>
			<ymax>608</ymax>
		</bndbox>
	</object>
	<object>
		<name>belt</name>
		<pose>Unspecified</pose>
		<truncated>0</truncated>
		<difficult>0</difficult>
		<bndbox>
			<xmin>1377</xmin>
			<ymin>176</ymin>
			<xmax>1462</xmax>
			<ymax>264</ymax>
		</bndbox>
	</object>
	<object>
		<name>head</name>
		<pose>Unspecified</pose>
		<truncated>0</truncated>
		<difficult>0</difficult>
		<bndbox>
			<xmin>2068</xmin>
			<ymin>536</ymin>
			<xmax>2198</xmax>
			<ymax>696</ymax>
		</bndbox>
	</object>
	<object>
		<name>helmet</name>
		<pose>Unspecified</pose>
		<truncated>0</truncated>
		<difficult>0</difficult>
		<bndbox>
			<xmin>2382</xmin>
			<ymin>749</ymin>
			<xmax>2504</xmax>
			<ymax>854</ymax>
		</bndbox>
	</object>
	<object>
		<name>belt</name>
		<pose>Unspecified</pose>
		<truncated>0</truncated>
		<difficult>0</difficult>
		<bndbox>
			<xmin>1939</xmin>
			<ymin>605</ymin>
			<xmax>2093</xmax>
			<ymax>778</ymax>
		</bndbox>
	</object>
	<object>
		<name>helmet</name>
		<pose>Unspecified</pose>
		<truncated>0</truncated>
		<difficult>0</difficult>
		<bndbox>
			<xmin>1469</xmin>
			<ymin>325</ymin>
			<xmax>1534</xmax>
			<ymax>377</ymax>
		</bndbox>
	</object>
	<object>
		<name>head</name>
		<pose>Unspecified</pose>
		<truncated>0</truncated>
		<difficult>0</difficult>
		<bndbox>
			<xmin>2355</xmin>
			<ymin>747</ymin>
			<xmax>2551</xmax>
			<ymax>1000</ymax>
		</bndbox>
	</object>
	<object>
		<name>helmet</name>
		<pose>Unspecified</pose>
		<truncated>0</truncated>
		<difficult>0</difficult>
		<bndbox>
			<xmin>1322</xmin>
			<ymin>136</ymin>
			<xmax>1382</xmax>
			<ymax>198</ymax>
		</bndbox>
	</object>
	<object>
		<name>people</name>
		<pose>Unspecified</pose>
		<truncated>0</truncated>
		<difficult>0</difficult>
		<bndbox>
			<xmin>288</xmin>
			<ymin>665</ymin>
			<xmax>456</xmax>
			<ymax>894</ymax>
		</bndbox>
	</object>
	<object>
		<name>helmet</name>
		<pose>Unspecified</pose>
		<truncated>0</truncated>
		<difficult>0</difficult>
		<bndbox>
			<xmin>1576</xmin>
			<ymin>406</ymin>
			<xmax>1652</xmax>
			<ymax>482</ymax>
		</bndbox>
	</object>
	<object>
		<name>head</name>
		<pose>Unspecified</pose>
		<truncated>0</truncated>
		<difficult>0</difficult>
		<bndbox>
			<xmin>1944</xmin>
			<ymin>515</ymin>
			<xmax>2120</xmax>
			<ymax>694</ymax>
		</bndbox>
	</object>
	<object>
		<name>people</name>
		<pose>Unspecified</pose>
		<truncated>0</truncated>
		<difficult>0</difficult>
		<bndbox>
			<xmin>1887</xmin>
			<ymin>515</ymin>
			<xmax>2133</xmax>
			<ymax>1104</ymax>
		</bndbox>
	</object>
	<object>
		<name>people</name>
		<pose>Unspecified</pose>
		<truncated>0</truncated>
		<difficult>0</difficult>
		<bndbox>
			<xmin>1331</xmin>
			<ymin>131</ymin>
			<xmax>1479</xmax>
			<ymax>404</ymax>
		</bndbox>
	</object>
	<object>
		<name>people</name>
		<pose>Unspecified</pose>
		<truncated>0</truncated>
		<difficult>0</difficult>
		<bndbox>
			<xmin>2303</xmin>
			<ymin>750</ymin>
			<xmax>2556</xmax>
			<ymax>1429</ymax>
		</bndbox>
	</object>
	<object>
		<name>people</name>
		<pose>Unspecified</pose>
		<truncated>0</truncated>
		<difficult>0</difficult>
		<bndbox>
			<xmin>1517</xmin>
			<ymin>404</ymin>
			<xmax>1726</xmax>
			<ymax>842</ymax>
		</bndbox>
	</object>
	<object>
		<name>truck</name>
		<pose>Unspecified</pose>
		<truncated>0</truncated>
		<difficult>0</difficult>
		<bndbox>
			<xmin>1160</xmin>
			<ymin>421</ymin>
			<xmax>2551</xmax>
			<ymax>1434</ymax>
		</bndbox>
	</object>
</annotation>
