<annotation>
	<folder>imges</folder>
	<filename>aimg580.jpg</filename>
	<path>C:\Users\Lenovo\Desktop\打标签\SK\imges\aimg580.jpg</path>
	<source>
		<database>Unknown</database>
	</source>
	<size>
		<width>2560</width>
		<height>1440</height>
		<depth>3</depth>
	</size>
	<segmented>0</segmented>
	<object>
		<name>helmet</name>
		<pose>Unspecified</pose>
		<truncated>0</truncated>
		<difficult>0</difficult>
		<bndbox>
			<xmin>343</xmin>
			<ymin>292</ymin>
			<xmax>375</xmax>
			<ymax>324</ymax>
		</bndbox>
	</object>
	<object>
		<name>head</name>
		<pose>Unspecified</pose>
		<truncated>0</truncated>
		<difficult>0</difficult>
		<bndbox>
			<xmin>319</xmin>
			<ymin>292</ymin>
			<xmax>384</xmax>
			<ymax>352</ymax>
		</bndbox>
	</object>
	<object>
		<name>head</name>
		<pose>Unspecified</pose>
		<truncated>0</truncated>
		<difficult>0</difficult>
		<bndbox>
			<xmin>1560</xmin>
			<ymin>200</ymin>
			<xmax>1674</xmax>
			<ymax>293</ymax>
		</bndbox>
	</object>
	<object>
		<name>helmet</name>
		<pose>Unspecified</pose>
		<truncated>0</truncated>
		<difficult>0</difficult>
		<bndbox>
			<xmin>1599</xmin>
			<ymin>197</ymin>
			<xmax>1659</xmax>
			<ymax>250</ymax>
		</bndbox>
	</object>
	<object>
		<name>belt</name>
		<pose>Unspecified</pose>
		<truncated>0</truncated>
		<difficult>0</difficult>
		<bndbox>
			<xmin>2170</xmin>
			<ymin>711</ymin>
			<xmax>2262</xmax>
			<ymax>816</ymax>
		</bndbox>
	</object>
	<object>
		<name>belt</name>
		<pose>Unspecified</pose>
		<truncated>0</truncated>
		<difficult>0</difficult>
		<bndbox>
			<xmin>1571</xmin>
			<ymin>241</ymin>
			<xmax>1661</xmax>
			<ymax>317</ymax>
		</bndbox>
	</object>
	<object>
		<name>helmet</name>
		<pose>Unspecified</pose>
		<truncated>0</truncated>
		<difficult>0</difficult>
		<bndbox>
			<xmin>2147</xmin>
			<ymin>653</ymin>
			<xmax>2239</xmax>
			<ymax>765</ymax>
		</bndbox>
	</object>
	<object>
		<name>head</name>
		<pose>Unspecified</pose>
		<truncated>0</truncated>
		<difficult>0</difficult>
		<bndbox>
			<xmin>2116</xmin>
			<ymin>655</ymin>
			<xmax>2287</xmax>
			<ymax>797</ymax>
		</bndbox>
	</object>
	<object>
		<name>people</name>
		<pose>Unspecified</pose>
		<truncated>0</truncated>
		<difficult>0</difficult>
		<bndbox>
			<xmin>317</xmin>
			<ymin>292</ymin>
			<xmax>388</xmax>
			<ymax>495</ymax>
		</bndbox>
	</object>
	<object>
		<name>people</name>
		<pose>Unspecified</pose>
		<truncated>0</truncated>
		<difficult>0</difficult>
		<bndbox>
			<xmin>2085</xmin>
			<ymin>652</ymin>
			<xmax>2322</xmax>
			<ymax>1057</ymax>
		</bndbox>
	</object>
	<object>
		<name>people</name>
		<pose>Unspecified</pose>
		<truncated>0</truncated>
		<difficult>0</difficult>
		<bndbox>
			<xmin>1517</xmin>
			<ymin>193</ymin>
			<xmax>1679</xmax>
			<ymax>568</ymax>
		</bndbox>
	</object>
	<object>
		<name>truck</name>
		<pose>Unspecified</pose>
		<truncated>0</truncated>
		<difficult>0</difficult>
		<bndbox>
			<xmin>1040</xmin>
			<ymin>98</ymin>
			<xmax>2553</xmax>
			<ymax>1439</ymax>
		</bndbox>
	</object>
	<object>
		<name>truck</name>
		<pose>Unspecified</pose>
		<truncated>1</truncated>
		<difficult>0</difficult>
		<bndbox>
			<xmin>888</xmin>
			<ymin>1</ymin>
			<xmax>1188</xmax>
			<ymax>295</ymax>
		</bndbox>
	</object>
</annotation>
