<annotation>
	<folder>D:/data/data_re_317/have_people</folder>
	<filename>allp20230407101216.jpg</filename>
	<path>D:/data/data_re_317/have_people/allp20230407101216.jpg</path>
	<source>
		<database>Unknown</database>
	</source>
	<size>
		<width>2560</width>
		<height>1440</height>
		<depth>3</depth>
	</size>
	<segmented>0</segmented>
	<object>
		<name>head</name>
		<pose>Unspecified</pose>
		<truncated>0</truncated>
		<difficult>0</difficult>
		<bndbox>
			<xmin>2181</xmin>
			<ymin>639</ymin>
			<xmax>2268</xmax>
			<ymax>733</ymax>
		</bndbox>
	</object>
	<object>
		<name>helmet</name>
		<pose>Unspecified</pose>
		<truncated>0</truncated>
		<difficult>0</difficult>
		<bndbox>
			<xmin>2199</xmin>
			<ymin>640</ymin>
			<xmax>2247</xmax>
			<ymax>678</ymax>
		</bndbox>
	</object>
	<object>
		<name>people</name>
		<pose>Unspecified</pose>
		<truncated>0</truncated>
		<difficult>0</difficult>
		<bndbox>
			<xmin>2140</xmin>
			<ymin>639</ymin>
			<xmax>2278</xmax>
			<ymax>976</ymax>
		</bndbox>
	</object>
</annotation>