<annotation>
	<folder>images</folder>
	<filename>allp20230407095529.jpg</filename>
	<path>E:\实训\YZJ\images\allp20230407095529.jpg</path>
	<source>
		<database>Unknown</database>
	</source>
	<size>
		<width>2560</width>
		<height>1440</height>
		<depth>3</depth>
	</size>
	<segmented>0</segmented>
	<object>
		<name>truck</name>
		<pose>Unspecified</pose>
		<truncated>1</truncated>
		<difficult>0</difficult>
		<bndbox>
			<xmin>1544</xmin>
			<ymin>1</ymin>
			<xmax>1749</xmax>
			<ymax>79</ymax>
		</bndbox>
	</object>
	<object>
		<name>helmet</name>
		<pose>Unspecified</pose>
		<truncated>0</truncated>
		<difficult>0</difficult>
		<bndbox>
			<xmin>2515</xmin>
			<ymin>150</ymin>
			<xmax>2545</xmax>
			<ymax>173</ymax>
		</bndbox>
	</object>
	<object>
		<name>helmet</name>
		<pose>Unspecified</pose>
		<truncated>0</truncated>
		<difficult>0</difficult>
		<bndbox>
			<xmin>2430</xmin>
			<ymin>189</ymin>
			<xmax>2459</xmax>
			<ymax>213</ymax>
		</bndbox>
	</object>
	<object>
		<name>head</name>
		<pose>Unspecified</pose>
		<truncated>0</truncated>
		<difficult>0</difficult>
		<bndbox>
			<xmin>2411</xmin>
			<ymin>189</ymin>
			<xmax>2474</xmax>
			<ymax>248</ymax>
		</bndbox>
	</object>
	<object>
		<name>helmet</name>
		<pose>Unspecified</pose>
		<truncated>0</truncated>
		<difficult>0</difficult>
		<bndbox>
			<xmin>2285</xmin>
			<ymin>101</ymin>
			<xmax>2318</xmax>
			<ymax>128</ymax>
		</bndbox>
	</object>
	<object>
		<name>head</name>
		<pose>Unspecified</pose>
		<truncated>0</truncated>
		<difficult>0</difficult>
		<bndbox>
			<xmin>2276</xmin>
			<ymin>102</ymin>
			<xmax>2323</xmax>
			<ymax>168</ymax>
		</bndbox>
	</object>
	<object>
		<name>people</name>
		<pose>Unspecified</pose>
		<truncated>0</truncated>
		<difficult>0</difficult>
		<bndbox>
			<xmin>2234</xmin>
			<ymin>98</ymin>
			<xmax>2324</xmax>
			<ymax>235</ymax>
		</bndbox>
	</object>
	<object>
		<name>helmet</name>
		<pose>Unspecified</pose>
		<truncated>0</truncated>
		<difficult>0</difficult>
		<bndbox>
			<xmin>1792</xmin>
			<ymin>66</ymin>
			<xmax>1828</xmax>
			<ymax>92</ymax>
		</bndbox>
	</object>
	<object>
		<name>head</name>
		<pose>Unspecified</pose>
		<truncated>0</truncated>
		<difficult>0</difficult>
		<bndbox>
			<xmin>1767</xmin>
			<ymin>65</ymin>
			<xmax>1847</xmax>
			<ymax>141</ymax>
		</bndbox>
	</object>
	<object>
		<name>truck</name>
		<pose>Unspecified</pose>
		<truncated>1</truncated>
		<difficult>0</difficult>
		<bndbox>
			<xmin>8</xmin>
			<ymin>13</ymin>
			<xmax>1284</xmax>
			<ymax>1440</ymax>
		</bndbox>
	</object>
	<object>
		<name>head</name>
		<pose>Unspecified</pose>
		<truncated>0</truncated>
		<difficult>0</difficult>
		<bndbox>
			<xmin>2421</xmin>
			<ymin>267</ymin>
			<xmax>2486</xmax>
			<ymax>348</ymax>
		</bndbox>
	</object>
	<object>
		<name>helmet</name>
		<pose>Unspecified</pose>
		<truncated>0</truncated>
		<difficult>0</difficult>
		<bndbox>
			<xmin>2431</xmin>
			<ymin>269</ymin>
			<xmax>2471</xmax>
			<ymax>297</ymax>
		</bndbox>
	</object>
	<object>
		<name>head</name>
		<pose>Unspecified</pose>
		<truncated>0</truncated>
		<difficult>0</difficult>
		<bndbox>
			<xmin>2502</xmin>
			<ymin>152</ymin>
			<xmax>2555</xmax>
			<ymax>218</ymax>
		</bndbox>
	</object>
	<object>
		<name>people</name>
		<pose>Unspecified</pose>
		<truncated>1</truncated>
		<difficult>0</difficult>
		<bndbox>
			<xmin>2495</xmin>
			<ymin>152</ymin>
			<xmax>2560</xmax>
			<ymax>352</ymax>
		</bndbox>
	</object>
	<object>
		<name>people</name>
		<pose>Unspecified</pose>
		<truncated>1</truncated>
		<difficult>0</difficult>
		<bndbox>
			<xmin>1426</xmin>
			<ymin>1</ymin>
			<xmax>1512</xmax>
			<ymax>197</ymax>
		</bndbox>
	</object>
	<object>
		<name>people</name>
		<pose>Unspecified</pose>
		<truncated>0</truncated>
		<difficult>0</difficult>
		<bndbox>
			<xmin>2399</xmin>
			<ymin>259</ymin>
			<xmax>2489</xmax>
			<ymax>526</ymax>
		</bndbox>
	</object>
	<object>
		<name>people</name>
		<pose>Unspecified</pose>
		<truncated>0</truncated>
		<difficult>0</difficult>
		<bndbox>
			<xmin>1742</xmin>
			<ymin>64</ymin>
			<xmax>1859</xmax>
			<ymax>288</ymax>
		</bndbox>
	</object>
</annotation>
