<annotation>
	<folder>D:/data/data_re_317/have_people</folder>
	<filename>allp20230407095830.jpg</filename>
	<path>D:/data/data_re_317/have_people/allp20230407095830.jpg</path>
	<source>
		<database>Unknown</database>
	</source>
	<size>
		<width>2560</width>
		<height>1440</height>
		<depth>3</depth>
	</size>
	<segmented>0</segmented>
	<object>
		<name>people</name>
		<pose>Unspecified</pose>
		<truncated>0</truncated>
		<difficult>0</difficult>
		<bndbox>
			<xmin>1019</xmin>
			<ymin>58</ymin>
			<xmax>1048</xmax>
			<ymax>132</ymax>
		</bndbox>
	</object>
	<object>
		<name>truck</name>
		<pose>Unspecified</pose>
		<truncated>0</truncated>
		<difficult>0</difficult>
		<bndbox>
			<xmin>2</xmin>
			<ymin>147</ymin>
			<xmax>398</xmax>
			<ymax>881</ymax>
		</bndbox>
	</object>
	<object>
		<name>truck</name>
		<pose>Unspecified</pose>
		<truncated>0</truncated>
		<difficult>0</difficult>
		<bndbox>
			<xmin>446</xmin>
			<ymin>44</ymin>
			<xmax>951</xmax>
			<ymax>949</ymax>
		</bndbox>
	</object>
</annotation>