<annotation>
	<folder>images</folder>
	<filename>allp20230407100809.jpg</filename>
	<path>D:\JS\six\LZH\images\allp20230407100809.jpg</path>
	<source>
		<database>Unknown</database>
	</source>
	<size>
		<width>2560</width>
		<height>1440</height>
		<depth>3</depth>
	</size>
	<segmented>0</segmented>
	<object>
		<name>head</name>
		<pose>Unspecified</pose>
		<truncated>0</truncated>
		<difficult>0</difficult>
		<bndbox>
			<xmin>2008</xmin>
			<ymin>1189</ymin>
			<xmax>2169</xmax>
			<ymax>1398</ymax>
		</bndbox>
	</object>
	<object>
		<name>helmet</name>
		<pose>Unspecified</pose>
		<truncated>0</truncated>
		<difficult>0</difficult>
		<bndbox>
			<xmin>2072</xmin>
			<ymin>1187</ymin>
			<xmax>2157</xmax>
			<ymax>1266</ymax>
		</bndbox>
	</object>
	<object>
		<name>truck</name>
		<pose>Unspecified</pose>
		<truncated>0</truncated>
		<difficult>0</difficult>
		<bndbox>
			<xmin>834</xmin>
			<ymin>13</ymin>
			<xmax>1340</xmax>
			<ymax>681</ymax>
		</bndbox>
	</object>
</annotation>
