<annotation>
	<folder>images</folder>
	<filename>allp20230407095842.jpg</filename>
	<path>C:\Users\Lenovo\Desktop\SK\images\allp20230407095842.jpg</path>
	<source>
		<database>Unknown</database>
	</source>
	<size>
		<width>2560</width>
		<height>1440</height>
		<depth>3</depth>
	</size>
	<segmented>0</segmented>
	<object>
		<name>truck</name>
		<pose>Unspecified</pose>
		<truncated>0</truncated>
		<difficult>0</difficult>
		<bndbox>
			<xmin>1220</xmin>
			<ymin>2</ymin>
			<xmax>1478</xmax>
			<ymax>111</ymax>
		</bndbox>
	</object>
	<object>
		<name>truck</name>
		<pose>Unspecified</pose>
		<truncated>1</truncated>
		<difficult>0</difficult>
		<bndbox>
			<xmin>1620</xmin>
			<ymin>1</ymin>
			<xmax>2109</xmax>
			<ymax>718</ymax>
		</bndbox>
	</object>
	<object>
		<name>helmet</name>
		<pose>Unspecified</pose>
		<truncated>0</truncated>
		<difficult>0</difficult>
		<bndbox>
			<xmin>1738</xmin>
			<ymin>501</ymin>
			<xmax>1786</xmax>
			<ymax>538</ymax>
		</bndbox>
	</object>
	<object>
		<name>head</name>
		<pose>Unspecified</pose>
		<truncated>0</truncated>
		<difficult>0</difficult>
		<bndbox>
			<xmin>1740</xmin>
			<ymin>502</ymin>
			<xmax>1816</xmax>
			<ymax>595</ymax>
		</bndbox>
	</object>
	<object>
		<name>people</name>
		<pose>Unspecified</pose>
		<truncated>0</truncated>
		<difficult>0</difficult>
		<bndbox>
			<xmin>1730</xmin>
			<ymin>496</ymin>
			<xmax>1821</xmax>
			<ymax>804</ymax>
		</bndbox>
	</object>
</annotation>
